tydier/__init__.py
tydier/catvars.py
tydier/numvars.py
tydier/strings.py
tydier/utilities.py
tydier-0.1.6.dist-info/LICENSE
tydier-0.1.6.dist-info/WHEEL
tydier-0.1.6.dist-info/METADATA
tydier-0.1.6.dist-info/RECORD
