Metadata-Version: 2.1
Name: tydier
Version: 0.1.6
Summary: Python package for easy data cleaning operations.
License: MIT
Author: Antonio Buzzelli
Requires-Python: >=3.9,<4.0
Classifier: License :: OSI Approved :: MIT License
Classifier: Programming Language :: Python :: 3
Classifier: Programming Language :: Python :: 3.9
Classifier: Programming Language :: Python :: 3.10
Requires-Dist: pandas (>=1.4.4,<2.0.0)
